{
    "ClassName": "",
    "Include": "",
    "Chance": 1,
    "Quantity": {
        "Min": 0,
        "Max": 0
    },
    "Health": [],
    "InventoryAttachments": [
        {
            "SlotName": "Headgear",
            "Items": [
                {
                    "ClassName": "BeanieHat_Black",
                    "Include": "",
                    "Chance": 1,
                    "Quantity": {
                        "Min": 0,
                        "Max": 0
                    },
                    "Health": [
                        {
                            "Min": 0.7,
                            "Max": 1,
                            "Zone": ""
                        }
                    ],
                    "InventoryAttachments": [],
                    "InventoryCargo": [],
                    "ConstructionPartsBuilt": [],
                    "Sets": []
                },
                {
                    "ClassName": "BaseballCap_Blue",
                    "Include": "",
                    "Chance": 1,
                    "Quantity": {
                        "Min": 0,
                        "Max": 0
                    },
                    "Health": [
                        {
                            "Min": 0.7,
                            "Max": 1,
                            "Zone": ""
                        }
                    ],
                    "InventoryAttachments": [],
                    "InventoryCargo": [],
                    "ConstructionPartsBuilt": [],
                    "Sets": []
                },
                {
                    "ClassName": "DarkMotoHelmet_Black",
                    "Include": "",
                    "Chance": 1,
                    "Quantity": {
                        "Min": 0,
                        "Max": 0
                    },
                    "Health": [
                        {
                            "Min": 0.7,
                            "Max": 1,
                            "Zone": ""
                        }
                    ],
                    "InventoryAttachments": [],
                    "InventoryCargo": [],
                    "ConstructionPartsBuilt": [],
                    "Sets": []
                }
            ]
        },
        {
            "SlotName": "Body",
            "Items": [
                {
                    "ClassName": "QuiltedJacket_Blue",
                    "Include": "",
                    "Chance": 1,
                    "Quantity": {
                        "Min": 0,
                        "Max": 0
                    },
                    "Health": [
                        {
                            "Min": 0.7,
                            "Max": 1,
                            "Zone": ""
                        }
                    ],
                    "InventoryAttachments": [],
                    "InventoryCargo": [],
                    "ConstructionPartsBuilt": [],
                    "Sets": []
                },
                {
                    "ClassName": "BomberJacket_Blue",
                    "Include": "",
                    "Chance": 1,
                    "Quantity": {
                        "Min": 0,
                        "Max": 0
                    },
                    "Health": [
                        {
                            "Min": 0.7,
                            "Max": 1,
                            "Zone": ""
                        }
                    ],
                    "InventoryAttachments": [],
                    "InventoryCargo": [],
                    "ConstructionPartsBuilt": [],
                    "Sets": []
                },
                {
                    "ClassName": "TrackSuitJacket_Red",
                    "Include": "",
                    "Chance": 1,
                    "Quantity": {
                        "Min": 0,
                        "Max": 0
                    },
                    "Health": [
                        {
                            "Min": 0.7,
                            "Max": 1,
                            "Zone": ""
                        }
                    ],
                    "InventoryAttachments": [],
                    "InventoryCargo": [],
                    "ConstructionPartsBuilt": [],
                    "Sets": []
                },
                {
                    "ClassName": "LeatherJacket_Black",
                    "Include": "",
                    "Chance": 1,
                    "Quantity": {
                        "Min": 0,
                        "Max": 0
                    },
                    "Health": [
                        {
                            "Min": 0.7,
                            "Max": 1,
                            "Zone": ""
                        }
                    ],
                    "InventoryAttachments": [],
                    "InventoryCargo": [],
                    "ConstructionPartsBuilt": [],
                    "Sets": []
                }
            ]
        },
        {
            "SlotName": "Vest",
            "Items": [
                {
                    "ClassName": "HighCapacityVest_Black",
                    "Include": "",
                    "Chance": 1,
                    "Quantity": {
                        "Min": 0,
                        "Max": 0
                    },
                    "Health": [
                        {
                            "Min": 0.7,
                            "Max": 1,
                            "Zone": ""
                        }
                    ],
                    "InventoryAttachments": [],
                    "InventoryCargo": [],
                    "ConstructionPartsBuilt": [],
                    "Sets": []
                }
            ]
        },
        {
            "SlotName": "Legs",
            "Items": [
                {
                    "ClassName": "Jeans_Blue",
                    "Include": "",
                    "Chance": 1,
                    "Quantity": {
                        "Min": 0,
                        "Max": 0
                    },
                    "Health": [
                        {
                            "Min": 0.7,
                            "Max": 1,
                            "Zone": ""
                        }
                    ],
                    "InventoryAttachments": [],
                    "InventoryCargo": [],
                    "ConstructionPartsBuilt": [],
                    "Sets": []
                },
                {
                    "ClassName": "Jeans_Black",
                    "Include": "",
                    "Chance": 1,
                    "Quantity": {
                        "Min": 0,
                        "Max": 0
                    },
                    "Health": [
                        {
                            "Min": 0.7,
                            "Max": 1,
                            "Zone": ""
                        }
                    ],
                    "InventoryAttachments": [],
                    "InventoryCargo": [],
                    "ConstructionPartsBuilt": [],
                    "Sets": []
                },
                {
                    "ClassName": "TrackSuitPants_Black",
                    "Include": "",
                    "Chance": 1,
                    "Quantity": {
                        "Min": 0,
                        "Max": 0
                    },
                    "Health": [
                        {
                            "Min": 0.7,
                            "Max": 1,
                            "Zone": ""
                        }
                    ],
                    "InventoryAttachments": [],
                    "InventoryCargo": [],
                    "ConstructionPartsBuilt": [],
                    "Sets": []
                }
            ]
        },
        {
            "SlotName": "Feet",
            "Items": [
                {
                    "ClassName": "JoggingShoes_White",
                    "Include": "",
                    "Chance": 1,
                    "Quantity": {
                        "Min": 0,
                        "Max": 0
                    },
                    "Health": [
                        {
                            "Min": 0.7,
                            "Max": 1,
                            "Zone": ""
                        }
                    ],
                    "InventoryAttachments": [],
                    "InventoryCargo": [],
                    "ConstructionPartsBuilt": [],
                    "Sets": []
                },
                {
                    "ClassName": "AthleticShoes_Black",
                    "Include": "",
                    "Chance": 1,
                    "Quantity": {
                        "Min": 0,
                        "Max": 0
                    },
                    "Health": [
                        {
                            "Min": 0.7,
                            "Max": 1,
                            "Zone": ""
                        }
                    ],
                    "InventoryAttachments": [],
                    "InventoryCargo": [],
                    "ConstructionPartsBuilt": [],
                    "Sets": []
                },
                {
                    "ClassName": "SneakersLow_Grey",
                    "Include": "",
                    "Chance": 1,
                    "Quantity": {
                        "Min": 0,
                        "Max": 0
                    },
                    "Health": [
                        {
                            "Min": 0.7,
                            "Max": 1,
                            "Zone": ""
                        }
                    ],
                    "InventoryAttachments": [],
                    "InventoryCargo": [],
                    "ConstructionPartsBuilt": [],
                    "Sets": []
                }
            ]
        },
        {
            "SlotName": "Back",
            "Items": [
                {
                    "ClassName": "CoyoteBag_Brown",
                    "Include": "",
                    "Chance": 1,
                    "Quantity": {
                        "Min": 0,
                        "Max": 0
                    },
                    "Health": [
                        {
                            "Min": 0.7,
                            "Max": 1,
                            "Zone": ""
                        }
                    ],
                    "InventoryAttachments": [],
                    "InventoryCargo": [],
                    "ConstructionPartsBuilt": [],
                    "Sets": []
                },
                {
                    "ClassName": "TaloonBag_Violet",
                    "Include": "",
                    "Chance": 1,
                    "Quantity": {
                        "Min": 0,
                        "Max": 0
                    },
                    "Health": [
                        {
                            "Min": 0.7,
                            "Max": 1,
                            "Zone": ""
                        }
                    ],
                    "InventoryAttachments": [],
                    "InventoryCargo": [],
                    "ConstructionPartsBuilt": [],
                    "Sets": []
                },
                {
                    "ClassName": "ChildBag_Blue",
                    "Include": "",
                    "Chance": 1,
                    "Quantity": {
                        "Min": 0,
                        "Max": 0
                    },
                    "Health": [
                        {
                            "Min": 0.7,
                            "Max": 1,
                            "Zone": ""
                        }
                    ],
                    "InventoryAttachments": [],
                    "InventoryCargo": [],
                    "ConstructionPartsBuilt": [],
                    "Sets": []
                }
            ]
        },
        {
            "SlotName": "Hands",
            "Items": [
                {
                    "ClassName": "CZ75",
                    "Include": "",
                    "Chance": 1,
                    "Quantity": {
                        "Min": 0,
                        "Max": 0
                    },
                    "Health": [],
                    "InventoryAttachments": [
                        {
                            "SlotName": "",
                            "Items": [
                                {
                                    "ClassName": "Mag_CZ75_15Rnd",
                                    "Include": "",
                                    "Chance": 1,
                                    "Quantity": {
                                        "Min": 0,
                                        "Max": 0
                                    },
                                    "Health": [],
                                    "InventoryAttachments": [],
                                    "InventoryCargo": [],
                                    "ConstructionPartsBuilt": [],
                                    "Sets": []
                                }
                            ]
                        }
                    ],
                    "InventoryCargo": [],
                    "ConstructionPartsBuilt": [],
                    "Sets": []
                },
                {
                    "ClassName": "Colt1911",
                    "Include": "",
                    "Chance": 1,
                    "Quantity": {
                        "Min": 0,
                        "Max": 0
                    },
                    "Health": [],
                    "InventoryAttachments": [
                        {
                            "SlotName": "",
                            "Items": [
                                {
                                    "ClassName": "Mag_1911_7Rnd",
                                    "Include": "",
                                    "Chance": 1,
                                    "Quantity": {
                                        "Min": 0,
                                        "Max": 0
                                    },
                                    "Health": [],
                                    "InventoryAttachments": [],
                                    "InventoryCargo": [],
                                    "ConstructionPartsBuilt": [],
                                    "Sets": []
                                }
                            ]
                        }
                    ],
                    "InventoryCargo": [],
                    "ConstructionPartsBuilt": [],
                    "Sets": []
                },
                {
                    "ClassName": "MakarovIJ70",
                    "Include": "",
                    "Chance": 1,
                    "Quantity": {
                        "Min": 0,
                        "Max": 0
                    },
                    "Health": [],
                    "InventoryAttachments": [
                        {
                            "SlotName": "",
                            "Items": [
                                {
                                    "ClassName": "Mag_IJ70_8Rnd",
                                    "Include": "",
                                    "Chance": 1,
                                    "Quantity": {
                                        "Min": 0,
                                        "Max": 0
                                    },
                                    "Health": [],
                                    "InventoryAttachments": [],
                                    "InventoryCargo": [],
                                    "ConstructionPartsBuilt": [],
                                    "Sets": []
                                }
                            ]
                        }
                    ],
                    "InventoryCargo": [],
                    "ConstructionPartsBuilt": [],
                    "Sets": []
                }
            ]
        }
    ],
    "InventoryCargo": [
        {
            "ClassName": "Rag",
            "Include": "",
            "Chance": 0.5,
            "Quantity": {
                "Min": 0,
                "Max": 0
            },
            "Health": [],
            "InventoryAttachments": [],
            "InventoryCargo": [],
            "ConstructionPartsBuilt": [],
            "Sets": []
        }
    ],
    "ConstructionPartsBuilt": [],
    "Sets": []
}
